_pointers.cpython-311-i386-linux-musl.so
pointers/base_pointers.py
pointers/decay.py
pointers/__init__.py
pointers/structure.py
pointers/custom_binding.py
pointers/c_pointer.py
pointers/_utils.py
pointers/magic.py
pointers/calloc.py
pointers/py.typed
pointers/malloc.py
pointers/object_pointer.py
pointers/bindings.py
pointers/_cstd.py
pointers/_pyapi.py
pointers/exceptions.py
pointers/api_bindings.py
pointers/stack_pointer.py
pointers/std_structs.py
pointers/util.py
pointers/var_pointer.py
pointers.py-3.0.1.dist-info/RECORD
pointers.py-3.0.1.dist-info/METADATA
pointers.py-3.0.1.dist-info/WHEEL
pointers.py-3.0.1.dist-info/top_level.txt
pointers.py-3.0.1.dist-info/LICENSE
