Metadata-Version: 2.1
Name: pointers.py
Version: 3.0.1
Author-email: ZeroIntensity <zintensitydev@gmail.com>
License: MIT License
Project-URL: Documentation, https://pointers.zintensity.dev
Project-URL: Issues, https://github.com/ZeroIntensity/pointers.py/issues
Project-URL: Source, https://github.com/ZeroIntensity/pointers.py
Keywords: python,pointers
Classifier: Programming Language :: Python
Classifier: Programming Language :: Python :: 3.8
Classifier: Programming Language :: Python :: 3.9
Classifier: Programming Language :: Python :: 3.10
Classifier: Programming Language :: Python :: 3.11
Classifier: Programming Language :: Python :: 3.12
Classifier: Programming Language :: Python :: Implementation :: CPython
License-File: LICENSE
Requires-Dist: typing-extensions
Requires-Dist: varname
